{
  "type": "house",
  "title": "Apartments complex for Sale",
  "location": " Mahasen Mawatha, Colombo 5",
  "price": "Rs. 180,000,000",
  "details": "<p>Fully Furnished Apartments in Colombo 5 for Sale.<br>\nThree storey building with Roof Top Terrace and 02 Three Bedroom Apartments , 01 Two Bedroom Apartment and also 01 single room Studio. All are fully equipped with Fridge,Cooker, Microwave, Washing machine, air-conditioning and also plates and cutleries. <br>\nVery popular among foriegn deligates.</p>"
}