{
  "type": "house",
  "title": "Beach villa at Boossa",
  "location": " Boossa",
  "price": "Rs. 101,500,000",
  "details": "<p>This three bed, three bath villa sits directly on the beach at Boossa near Galle.\u00a0 Currently run as a holiday let it is offered for sale fully-furnished and equipped.<br>\n<br>\nThe accommodation comprises three bedrooms each with bathroom, large living and dining areas, kitchen and outside terrace.\u00a0 All rooms are air-conditioned. Outside there is a swimming pool and a separate pavilion perfect for lounging or al-fresco dining.\u00a0 The large garden which contains several coconut palms,\u00a0 opens directly on to the beach.<br>\n<br>\nThe villa is equipped with hot water, store rooms, a laundry and staff facilities.</p>"
}