{
  "type": "land",
  "title": "land for sale - Colombo 4 | LKR 15,000,000pp",
  "location": " Colombo 4",
  "price": "Rs. 15,000,000",
  "details": "<p>Land for sale - Colombo 4<br>\n<br>\n- 22 Perches<br>\n- Land with house<br>\n- Sold at land value<br>\n- Electricity and water connection<br>\n<br>\nTo let us know how we can assist with your land search please call us, on +94 779 225 255 / +94 777 60 20 30 or email us at sales@acquest.lk we will be happy to assist with more information and arrange a viewings.</p>"
}