{
  "type": "land",
  "title": "Land for Sale in Rajagiriya",
  "location": " Meda Welikada, Rajagiriya",
  "price": "Rs. 3,000,000",
  "details": "<p>Highly Residential Property in Rajagiriya<br>\nClear Deed / Calm &amp; quite area / Good Neighborhood<br>\nNear supermarkets, Banks,hospitals, School,<br>\n300 M to Rajagiriya Road<br>\n500 m to Borella - Rajagiriya Rd<br>\n18 - 20 feet wide road access<br>\n<br>\nTotal land - 23 Perches ( 8 and 15 perch plots can be blocked out)<br>\n<br>\nPrice Rs 2.6 Million per Perch<br>\n<br>\nStrictly No Brokers<br>\n<br>\nPlease call for more information<br>\n<br>\nExclusively sold by -<br>\n<br>\nPAN GLOBAL PROPERTY DEVELOPERS (PVT) LTD<br>\n351 ,DUPLICATION ROAD ,<br>\nCOLOMBO 03<br>\n<br>\n</p>"
}