{
  "type": "land",
  "title": "Land with 3 Houses for sale @ Beddagana",
  "location": " Beddagana, Ethul Kotte",
  "price": "Rs. 2,000,000",
  "details": "<p>Land with 3 Houses for sale @ Beddagana<br>\n<br>\n\u2022 19 Perches rectangle land<br>\n<br>\n\u2022 30 Feet wide Carpet Road<br>\n<br>\n\u2022 Having Separate 3 Houses<br>\n<br>\n\u2022 right-round parapet walls right-round parapet walls<br>\n<br>\n\u2022 Separate Electricity / Water &amp; 3 assesmen numbers<br>\n<br>\n\u2022 Calm &amp; Quit Residential Area<br>\n<br>\n\u2022 600m To Kotte Thalawatugoda Road<br>\n\u2022 1.2km to Kotte Junction<br>\n<br>\nper perch - 20 Laks (Negotiable) <br>\nTotal value - 380 Laks (Negotiable)</p>"
}