{
  "type": "land",
  "title": "Land for Sale in Battaramulla",
  "location": " Pahalawela Road, Battaramulla",
  "price": "Rs. 2,800,000",
  "details": "<p>Land for Sale in Pahalawela Road [Off Japan Sri Lanka Friendship Road]<br>\n<br>\nHighlights<br>\n- Land extent: c. 35.43 Perches<br>\n- Property is located on Pahalawela Road, Battaramulla.<br>\n- The property is accessible via a 20 foot wide access road. <br>\n- Access via Japan Sri Lanka Friendship Road [500 meters away]<br>\n- Access via Parliament Road [500 meters away]<br>\n<br>\nDetails<br>\n- Bare land.<br>\n- Water &amp; electricity accessible.<br>\n- Clear title.</p>"
}