{
  "type": "land",
  "title": "Land for Sale within Kandy City Limit",
  "location": " Wattaranthanne., Kandy",
  "price": "Rs. 1,100,000",
  "details": "<p>Here is an opportunity to buy a land with a breathtaking view of the Mahaweli river and in close proximity to the cinnamon citadel hotel.<br>\n<br>\n-3 minute distance from Kandy City Centre<br>\n-located in Samadi Mawatha<br>\n-direct access from carpet road<br>\n-suitable for residential or commercial purposes<br>\n-calm and peaceful area<br>\n<br>\nThis land is being sold with the value for the land only. THE HOUSE (1 BEDROOM WITH AN ATTACHED BATHROOM) COMES WITH NO ADDITIONAL PAYMENTS. <br>\n<br>\nFor more information, please call the number listed.<br>\n0725300174 or 00971561861248<br>\n</p>"
}