{
  "type": "house",
  "title": "Luxury house for sale in Nugegoda Mirihana",
  "location": " Mirihana , Nugegoda",
  "price": "Rs. 25,000,000",
  "details": "<p>Luxury house for sale in Nugegoda Mirihana<br>\n2km from Mirihana police<br>\n2.4km from Nugegoda super market <br>\n<br>\n10.9 perches<br>\n6 bedrooms 4 bathrooms<br>\n2units separate <br>\nRoof fully wood finish<br>\nLovely pantry <br>\nDinning and large hall<br>\nLarge balcony front<br>\nGarden space<br>\nRoller shutter gate with 2 parking <br>\nSeparate maid\u2019s room and bathroom<br>\n<br>\nPhotos can be sent only for interested parties<br>\nIf interested fix an appointment for inspection <br>\n<br>\nNO BROKERS\t<br>\nPrice 25 mil (nego)<br>\nCall or whatsapp \u2013 0772805053<br>\n</p>"
}