{
  "type": "house",
  "title": "Penthouse for Sale - Green Elegance, Thalawathugoda",
  "location": " Wanaguru Mawatha, Hokandara",
  "price": "Rs. 25,000,000",
  "details": "<p>This is a newly constructed Penthouse<br>\n<br>\n2,400Sq.ft. Duplex Penthouse located on the 6th and 7th Floor<br>\n4 Bedrooms and 4 Bathrooms<br>\nDedicated plunge pool with Jacuzzi within the Penthouse<br>\nLarge private rooftop area<br>\nFully Air-conditioned (05 AC units)<br>\nSwimming pool and Gymnasium<br>\nMaid's room and washroom<br>\n02 dedicated parking slots<br>\n1Km to Athurugiriya expressway entrance<br>\nStandby Generator<br>\n24 Hour Security with CCTv Surveillance<br>\n<br>\n<br>\nExpecting Rs. 25 Million (Negotiable)<br>\n<br>\nFor more details please contact. +94777407408 / +940777632672.<br>\n<br>\nSerene Properties<br>\nSerene Holdings (Private) Limited<br>\n\"Your Trusted Real Estate Service Provider\"</p>"
}