{
  "type": "house",
  "title": "TRILLIUM 7 | 3 BR | FF - L1 - 1707 Sq.ft | Colombo 07 | Apartment For Sale !",
  "location": " No : 230 , Torrington Avenue , Colombo 7",
  "price": "",
  "details": "<p>TRILLIUM 7<br>\nColombo 07.<br>\n<br>\nUnit Type -<br>\n3 BedRooms | FullyFurnished | 1707 Sq.Ft<br>\n1 Attached BathRoom | 1 Common BathRoom<br>\nMaid RestRoom OR Utility Room &amp; Toilet<br>\nUtility Area<br>\nLiving | Dining | Fully Fitted Pantry Kitchen<br>\nBalcony<br>\n<br>\nPool / Gym / CarPark / RoofTop / Lift / 24 Hrs Security / BackUp Generator / BackUp WaterTank<br>\n<br>\nSelling Offer -<br>\nNegotiable.<br>\n<br>\nNotes -<br>\n\u300bTitle Deed | Certificate Of Conformity ( COC ) Available.<br>\n<br>\n\u300bVacant Possession.</p>"
}