{
  "type": "land",
  "title": "Very Good Property to Buy in Pitipana-Homagama",
  "location": " Pitipana, Homagama",
  "price": "Rs. 26,000,000",
  "details": "<p>This is a 96P property with a single storied 3 bedroom house built in the year 1999 now available for quick sale.<br>\nThe location off Moragahahena Road on a 20' wide road access only 5 minutes drive (1.80km) to Pitipana Junction and further 4 minutes drive (1.60km) to Homaga Town.<br>\n<br>\nFull Details of the House :- 1,722sqft floor area, 3 bedroom, hall, dinning area, garage, kitchen(no pantry cupboard), Terrazzo floor, bed rooms fully tiled with wall cabinets. The house wood ceiling (lunumidella) , well water with over head tank ( main line water will be available soon).<br>\n<br>\nLand Extent : 96 Perches<br>\n<br>\nSelling Price : LKR 26 Million(ONO)<br>\n<br>\nNO BROKERS/AGENTS PLEASE<br>\n<br>\n</p>"
}